physplot/__init__.py
physplot/error.py
physplot/graph.py
physplot/propagation.py
physplot-0.1.1.dist-info/METADATA
physplot-0.1.1.dist-info/WHEEL
physplot-0.1.1.dist-info/top_level.txt
physplot-0.1.1.dist-info/RECORD
